django_readers/__init__.py
django_readers/pairs.py
django_readers/producers.py
django_readers/projectors.py
django_readers/qs.py
django_readers/rest_framework.py
django_readers/specs.py
django_readers/utils.py
django_readers-2.5.1.dist-info/LICENSE
django_readers-2.5.1.dist-info/METADATA
django_readers-2.5.1.dist-info/WHEEL
django_readers-2.5.1.dist-info/top_level.txt
django_readers-2.5.1.dist-info/RECORD
