Metadata-Version: 2.1
Name: django-readers
Version: 2.5.1
Summary: A lightweight function-oriented toolkit for better organisation of business logic and efficient selection and projection of data in Django projects.
Home-page: https://www.django-readers.org
Author: DabApps
Author-email: hello@dabapps.com
License: BSD
Project-URL: Changelog, https://github.com/dabapps/django-readers/releases
Project-URL: Issues, https://github.com/dabapps/django-readers/issues
Platform: UNKNOWN
Requires-Python: >=3.6
Requires-Dist: Django>=3.2
